odoo/addons/stock_orderpoint_default_location/README.rst
odoo/addons/stock_orderpoint_default_location/__init__.py
odoo/addons/stock_orderpoint_default_location/__manifest__.py
odoo/addons/stock_orderpoint_default_location/i18n/fr.po
odoo/addons/stock_orderpoint_default_location/i18n/it.po
odoo/addons/stock_orderpoint_default_location/i18n/stock_orderpoint_default_location.pot
odoo/addons/stock_orderpoint_default_location/i18n/tr.po
odoo/addons/stock_orderpoint_default_location/models/__init__.py
odoo/addons/stock_orderpoint_default_location/models/stock_warehouse.py
odoo/addons/stock_orderpoint_default_location/models/stock_warehouse_orderpoint.py
odoo/addons/stock_orderpoint_default_location/readme/CONFIGURE.md
odoo/addons/stock_orderpoint_default_location/readme/CONTEXT.md
odoo/addons/stock_orderpoint_default_location/readme/CONTRIBUTORS.md
odoo/addons/stock_orderpoint_default_location/readme/DESCRIPTION.md
odoo/addons/stock_orderpoint_default_location/static/description/icon.png
odoo/addons/stock_orderpoint_default_location/static/description/index.html
odoo/addons/stock_orderpoint_default_location/tests/__init__.py
odoo/addons/stock_orderpoint_default_location/tests/test_orderpoint_default.py
odoo/addons/stock_orderpoint_default_location/views/stock_warehouse.xml
odoo_addon_stock_orderpoint_default_location-18.0.1.0.1.dist-info/METADATA
odoo_addon_stock_orderpoint_default_location-18.0.1.0.1.dist-info/WHEEL
odoo_addon_stock_orderpoint_default_location-18.0.1.0.1.dist-info/top_level.txt
odoo_addon_stock_orderpoint_default_location-18.0.1.0.1.dist-info/RECORD
