Metadata-Version: 2.1
Name: odoo-addon-stock_orderpoint_default_location
Version: 18.0.1.0.1
Requires-Python: >=3.10
Requires-Dist: odoo-addon-base_partition==18.0.*
Requires-Dist: odoo==18.0.*
Summary: This module allows to define a different default location than the stock location
Home-page: https://github.com/OCA/stock-logistics-orderpoint
License: AGPL-3
Author: ACSONE SA/NV,Odoo Community Association (OCA)
Author-email: support@odoo-community.org
Classifier: Programming Language :: Python
Classifier: Framework :: Odoo
Classifier: Framework :: Odoo :: 18.0
Classifier: License :: OSI Approved :: GNU Affero General Public License v3
